mcp_master/__init__.py
mcp_master/config.py
mcp_master/master_server/__init__.py
mcp_master/master_server/master_server.py
mcp_master/master_server/master_server_client.py
mcp_master/orchestration/__init__.py
mcp_master/orchestration/agent_protocol.py
mcp_master/orchestration/agents.py
mcp_master/orchestration/orchestration.py
mcp_master-0.0.9.dist-info/METADATA
mcp_master-0.0.9.dist-info/WHEEL
mcp_master-0.0.9.dist-info/licenses/LICENSE
mcp_master-0.0.9.dist-info/RECORD
